pineflow/llms/litellm/__init__.py
pineflow/llms/litellm/base.py
pineflow_llms_litellm-0.7.2.dist-info/METADATA
pineflow_llms_litellm-0.7.2.dist-info/WHEEL
pineflow_llms_litellm-0.7.2.dist-info/RECORD
