Metadata-Version: 2.4
Name: pineflow-llms-litellm
Version: 0.7.2
Summary: pineflow llms litellm extension
Author-email: Leonardo Furnielis <leonardofurnielis@outlook.com>
License: MIT
Requires-Python: <4.0,>=3.10
Requires-Dist: litellm<2.0.0,>=1.73.2
Requires-Dist: pineflow-core<0.8.0,>=0.7.5
Provides-Extra: dev
Requires-Dist: ruff>=0.11.13; extra == 'dev'
